brainpy_state/__init__.py
brainpy_state/_base.py
brainpy_state/_base_test.py
brainpy_state/_exponential.py
brainpy_state/_hh.py
brainpy_state/_hh_test.py
brainpy_state/_inputs.py
brainpy_state/_izhikevich.py
brainpy_state/_izhikevich_test.py
brainpy_state/_lif.py
brainpy_state/_lif_test.py
brainpy_state/_misc.py
brainpy_state/_mixin.py
brainpy_state/_projection.py
brainpy_state/_readout.py
brainpy_state/_readout_test.py
brainpy_state/_stp.py
brainpy_state/_synapse.py
brainpy_state/_synapse_test.py
brainpy_state/_synaptic_projection.py
brainpy_state/_synouts.py
brainpy_state/_synouts_test.py
brainpy_state-0.0.3.dist-info/licenses/LICENSE
brainpy_state-0.0.3.dist-info/WHEEL
brainpy_state-0.0.3.dist-info/METADATA
brainpy_state-0.0.3.dist-info/RECORD
