Metadata-Version: 2.4
Name: brainpy_state
Version: 0.0.3
Summary: brainpy.state: stateful spiking neural network models in BrainPy
Keywords: computational neuroscience,brain-inspired computation,brain modeling,brain dynamics modeling,brain dynamics programming
Author-email: BrainX Team <chao.brain@qq.com>
Requires-Python: >=3.10
Classifier: Natural Language :: English
Classifier: Operating System :: OS Independent
Classifier: Programming Language :: Python
Classifier: Programming Language :: Python :: 3
Classifier: Programming Language :: Python :: 3.10
Classifier: Programming Language :: Python :: 3.11
Classifier: Programming Language :: Python :: 3.12
Classifier: Programming Language :: Python :: 3.13
Classifier: Programming Language :: Python :: 3.14
Classifier: Intended Audience :: Science/Research
Classifier: Topic :: Scientific/Engineering :: Bio-Informatics
Classifier: Topic :: Scientific/Engineering :: Mathematics
Classifier: Topic :: Scientific/Engineering :: Artificial Intelligence
Classifier: Topic :: Software Development :: Libraries
License-File: LICENSE
Requires-Dist: numpy>=1.15
Requires-Dist: jax
Requires-Dist: tqdm
Requires-Dist: brainpy>=2.7.5
Requires-Dist: brainstate>=0.2.0
Requires-Dist: brainunit
Requires-Dist: brainevent>=0.0.4
Requires-Dist: braintools>=0.0.9
Requires-Dist: jax[cpu] ; extra == "cpu"
Requires-Dist: brainstate ; extra == "cpu"
Requires-Dist: brainunit ; extra == "cpu"
Requires-Dist: brainevent ; extra == "cpu"
Requires-Dist: braintools ; extra == "cpu"
Requires-Dist: brainpy>=2.7.5 ; extra == "cpu"
Requires-Dist: jax[cuda12] ; extra == "cuda12"
Requires-Dist: brainstate ; extra == "cuda12"
Requires-Dist: brainunit ; extra == "cuda12"
Requires-Dist: brainevent ; extra == "cuda12"
Requires-Dist: braintools ; extra == "cuda12"
Requires-Dist: brainpy>=2.7.5 ; extra == "cuda12"
Requires-Dist: jax[cuda13] ; extra == "cuda13"
Requires-Dist: brainstate ; extra == "cuda13"
Requires-Dist: brainunit ; extra == "cuda13"
Requires-Dist: brainevent ; extra == "cuda13"
Requires-Dist: braintools ; extra == "cuda13"
Requires-Dist: brainpy>=2.7.5 ; extra == "cuda13"
Requires-Dist: jax[tpu] ; extra == "tpu"
Requires-Dist: brainstate ; extra == "tpu"
Requires-Dist: brainunit ; extra == "tpu"
Requires-Dist: brainevent ; extra == "tpu"
Requires-Dist: braintools ; extra == "tpu"
Requires-Dist: brainpy>=2.7.5 ; extra == "tpu"
Project-URL: Bug Tracker, https://github.com/chaobrain/brainpy.state/issues
Project-URL: Documentation, https://brainpy-state.readthedocs.io/
Project-URL: Source Code, https://github.com/chaobrain/brainpy.state
Provides-Extra: cpu
Provides-Extra: cuda12
Provides-Extra: cuda13
Provides-Extra: tpu
